santaHog/__init__.py
santaHog/npmSearcher.py
santaHog/pypiSearcher.py
santaHog/santaHog.py
santaHog/scan_archives.py
santaHog-0.0.0.dist-info/DESCRIPTION.rst
santaHog-0.0.0.dist-info/METADATA
santaHog-0.0.0.dist-info/RECORD
santaHog-0.0.0.dist-info/WHEEL
santaHog-0.0.0.dist-info/entry_points.txt
santaHog-0.0.0.dist-info/metadata.json
santaHog-0.0.0.dist-info/top_level.txt
