Metadata-Version: 2.0
Name: santaHog
Version: 0.0.0
Summary: Searches through package revision history for secrets.
Home-page: https://github.com/dxa4481/santaHog
Author: Dylan Ayrey
Author-email: dylanayrey@gmail.com
License: GNU
Platform: UNKNOWN
Requires-Dist: truffleHogRegexes (==0.0.4)
Requires-Dist: beautifulsoup4 (==4.6.0)
Requires-Dist: requests (==2.18.4)
